[
  {
    "comment_content": "I've always been intrigued by these tech advancements. This post just fueled my passion.",
    "user_id": 5,
    "post_id": 3,
    "comment_date": "2023-06-11 10:05:00"
  },
  {
    "comment_content": "Every time I read about such innovations, I get excited about the future. Great post!",
    "user_id": 3,
    "post_id": 9,
    "comment_date": "2023-06-12 10:05:00"
  },
  {
    "comment_content": "The pace at which technology is advancing is truly mesmerizing. Thanks for the insightful post.",
    "user_id": 9,
    "post_id": 7,
    "comment_date": "2023-06-13 10:05:00"
  },
  {
    "comment_content": "This article perfectly encapsulates the essence of the topic. Kudos to the writer!",
    "user_id": 8,
    "post_id": 2,
    "comment_date": "2023-06-14 10:05:00"
  },
  {
    "comment_content": "Every day we're stepping into the future. Such innovations are a testament to that. Great read!",
    "user_id": 2,
    "post_id": 4,
    "comment_date": "2023-06-15 10:05:00"
  },
  {
    "comment_content": "I'm always on the lookout for tech insights, and this post didn't disappoint. Brilliantly penned!",
    "user_id": 4,
    "post_id": 10,
    "comment_date": "2023-06-16 10:05:00"
  },
  {
    "comment_content": "The advancements discussed here are nothing short of revolutionary. Eager to witness them in action.",
    "user_id": 7,
    "post_id": 1,
    "comment_date": "2023-06-17 10:05:00"
  },
  {
    "comment_content": "Seeing such innovations, I'm optimistic about the technological future ahead. Great share!",
    "user_id": 6,
    "post_id": 5,
    "comment_date": "2023-06-18 10:05:00"
  },
  {
    "comment_content": "A well-structured post that offers deep insights. Much appreciated!",
    "user_id": 1,
    "post_id": 8,
    "comment_date": "2023-06-19 10:05:00"
  },
  {
    "comment_content": "Every time I think tech has peaked, I come across innovations like these. Astounding!",
    "user_id": 10,
    "post_id": 6,
    "comment_date": "2023-06-20 10:05:00"
  },
  {
    "comment_content": "This post offers such a wealth of information. I appreciate the insights!",
    "user_id": 3,
    "post_id": 5,
    "comment_date": "2023-06-21 10:05:00"
  },
  {
    "comment_content": "This article does a brilliant job breaking down complex concepts. Kudos!",
    "user_id": 6,
    "post_id": 2,
    "comment_date": "2023-06-22 10:05:00"
  },
  {
    "comment_content": "Every day we're getting closer to a tech-driven utopia with innovations like this.",
    "user_id": 8,
    "post_id": 9,
    "comment_date": "2023-06-23 10:05:00"
  },
  {
    "comment_content": "As someone deeply passionate about tech, I find this to be a must-read. Great job!",
    "user_id": 1,
    "post_id": 7,
    "comment_date": "2023-06-24 10:05:00"
  },
  {
    "comment_content": "It's surreal to see technology evolve at such a rapid pace in our times.",
    "user_id": 4,
    "post_id": 10,
    "comment_date": "2023-06-25 10:05:00"
  },
  {
    "comment_content": "This innovation is set to usher in a new era for the tech industry. Exciting!",
    "user_id": 9,
    "post_id": 3,
    "comment_date": "2023-06-26 10:05:00"
  },
  {
    "comment_content": "Thank you for enlightening us with this informative piece. Learned a lot!",
    "user_id": 5,
    "post_id": 1,
    "comment_date": "2023-06-27 10:05:00"
  },
  {
    "comment_content": "This feels like something straight out of a sci-fi novel. Truly futuristic!",
    "user_id": 7,
    "post_id": 8,
    "comment_date": "2023-06-28 10:05:00"
  },
  {
    "comment_content": "A game-changing tech development! It's set to make waves.",
    "user_id": 2,
    "post_id": 4,
    "comment_date": "2023-06-29 10:05:00"
  },
  {
    "comment_content": "This tech is a game-changer! It will redefine the industry within no time.",
    "user_id": 10,
    "post_id": 6,
    "comment_date": "2023-06-30 10:05:00"
  }
]
